taxsystem/__init__.py
taxsystem/admin.py
taxsystem/app_settings.py
taxsystem/apps.py
taxsystem/auth_hooks.py
taxsystem/decorators.py
taxsystem/errors.py
taxsystem/forms.py
taxsystem/hooks.py
taxsystem/providers.py
taxsystem/tasks.py
taxsystem/urls.py
taxsystem/views.py
taxsystem/api/__init__.py
taxsystem/api/admin.py
taxsystem/api/corporation.py
taxsystem/api/filters.py
taxsystem/api/logs.py
taxsystem/api/payments.py
taxsystem/api/schema.py
taxsystem/api/helpers/__init__.py
taxsystem/api/helpers/core.py
taxsystem/api/helpers/icons.py
taxsystem/api/helpers/statistics.py
taxsystem/helpers/__init__.py
taxsystem/helpers/lazy.py
taxsystem/locale/__init__.py
taxsystem/locale/django.pot
taxsystem/locale/cs_CZ/LC_MESSAGES/django.mo
taxsystem/locale/cs_CZ/LC_MESSAGES/django.po
taxsystem/locale/de/LC_MESSAGES/django.mo
taxsystem/locale/de/LC_MESSAGES/django.po
taxsystem/locale/es/LC_MESSAGES/django.mo
taxsystem/locale/es/LC_MESSAGES/django.po
taxsystem/locale/fr_FR/LC_MESSAGES/django.mo
taxsystem/locale/fr_FR/LC_MESSAGES/django.po
taxsystem/locale/it_IT/LC_MESSAGES/django.mo
taxsystem/locale/it_IT/LC_MESSAGES/django.po
taxsystem/locale/ja/LC_MESSAGES/django.mo
taxsystem/locale/ja/LC_MESSAGES/django.po
taxsystem/locale/ko_KR/LC_MESSAGES/django.mo
taxsystem/locale/ko_KR/LC_MESSAGES/django.po
taxsystem/locale/nl_NL/LC_MESSAGES/django.mo
taxsystem/locale/nl_NL/LC_MESSAGES/django.po
taxsystem/locale/pl_PL/LC_MESSAGES/django.mo
taxsystem/locale/pl_PL/LC_MESSAGES/django.po
taxsystem/locale/ru/LC_MESSAGES/django.mo
taxsystem/locale/ru/LC_MESSAGES/django.po
taxsystem/locale/sk/LC_MESSAGES/django.mo
taxsystem/locale/sk/LC_MESSAGES/django.po
taxsystem/locale/uk/LC_MESSAGES/django.mo
taxsystem/locale/uk/LC_MESSAGES/django.po
taxsystem/locale/zh_Hans/LC_MESSAGES/django.mo
taxsystem/locale/zh_Hans/LC_MESSAGES/django.po
taxsystem/management/__init__.py
taxsystem/management/commands/__init__.py
taxsystem/management/commands/taxsystem_cleanup_payments.py
aa_taxsystem-2.0.0.dist-info/METADATA
aa_taxsystem-2.0.0.dist-info/WHEEL
aa_taxsystem-2.0.0.dist-info/licenses/LICENSE
aa_taxsystem-2.0.0.dist-info/RECORD
